{
  "config": {
    "model_size": "175b",
    "model_config": {
      "hidden_size": 12288,
      "num_layers": 96,
      "num_attention_heads": 96,
      "seq_length": 2048
    },
    "data_parallel_size": 2,
    "tensor_model_parallel_size": 4,
    "pipeline_model_parallel_size": 6,
    "context_parallel_size": 1,
    "world_size": 48,
    "seed": 1234,
    "timestamp": "20250810_184348",
    "num_micro_batches": 4,
    "global_batch_size": 1024
  },
  "log_files": [
    "comm_log_rank_0.json",
    "comm_log_rank_1.json",
    "comm_log_rank_2.json",
    "comm_log_rank_3.json",
    "comm_log_rank_4.json",
    "comm_log_rank_5.json",
    "comm_log_rank_6.json",
    "comm_log_rank_7.json",
    "comm_log_rank_8.json",
    "comm_log_rank_9.json",
    "comm_log_rank_10.json",
    "comm_log_rank_11.json",
    "comm_log_rank_12.json",
    "comm_log_rank_13.json",
    "comm_log_rank_14.json",
    "comm_log_rank_15.json",
    "comm_log_rank_16.json",
    "comm_log_rank_17.json",
    "comm_log_rank_18.json",
    "comm_log_rank_19.json",
    "comm_log_rank_20.json",
    "comm_log_rank_21.json",
    "comm_log_rank_22.json",
    "comm_log_rank_23.json",
    "comm_log_rank_24.json",
    "comm_log_rank_25.json",
    "comm_log_rank_26.json",
    "comm_log_rank_27.json",
    "comm_log_rank_28.json",
    "comm_log_rank_29.json",
    "comm_log_rank_30.json",
    "comm_log_rank_31.json",
    "comm_log_rank_32.json",
    "comm_log_rank_33.json",
    "comm_log_rank_34.json",
    "comm_log_rank_35.json",
    "comm_log_rank_36.json",
    "comm_log_rank_37.json",
    "comm_log_rank_38.json",
    "comm_log_rank_39.json",
    "comm_log_rank_40.json",
    "comm_log_rank_41.json",
    "comm_log_rank_42.json",
    "comm_log_rank_43.json",
    "comm_log_rank_44.json",
    "comm_log_rank_45.json",
    "comm_log_rank_46.json",
    "comm_log_rank_47.json"
  ]
}